pabo/__init__.py
pabo/_version.py
pabo/base.py
pabo/bits.py
pabo/bytes.py
pabo/core.cp38-win_amd64.pyd
pabo/core.cpp
pabo/numeric.py
pabo/specify.py
pabo/strings.py
pabo/wrappers.py
pabo-0.1.3.dist-info/LICENSE
pabo-0.1.3.dist-info/METADATA
pabo-0.1.3.dist-info/WHEEL
pabo-0.1.3.dist-info/top_level.txt
pabo-0.1.3.dist-info/RECORD
