Metadata-Version: 2.1
Name: pabo
Version: 0.1.3
Summary: "Binary parsing for dummies!"
Home-page: https://github.com/astrogewgaw/pabo
Author: "Ujjwal Panda"
Author-email: "ujjwalpanda97@gmail.com"
License: MIT License
Project-URL: Source Code, https://github.com/astrogewgaw/pabo
Project-URL: Documentation, https://pabo.readthedocs.io/en/latest
Project-URL: Bug Reports, https://github.com/astrogewgaw/pabo/issues
Classifier: Operating System :: Unix
Classifier: Operating System :: MacOS :: MacOS X
Classifier: Programming Language :: Python :: 3.6
Classifier: Programming Language :: Python :: 3.7
Classifier: Programming Language :: Python :: 3.8
Classifier: Programming Language :: Python :: 3.9
Classifier: Programming Language :: Python :: 3.10
Classifier: Programming Language :: Python :: 3.11
Classifier: License :: OSI Approved :: MIT License
Requires-Python: >=3.6
License-File: LICENSE
Requires-Dist: attrs (>=20.1.0)
Requires-Dist: numpy (>=1.19.0)
